custom_inherit/__init__.py
custom_inherit/_decorator_base.py
custom_inherit/_metaclass_base.py
custom_inherit/_style_store.py
custom_inherit/_version.py
custom_inherit/_doc_parse_tools/__init__.py
custom_inherit/_doc_parse_tools/napoleon_parse_tools.py
custom_inherit/_doc_parse_tools/numpy_parse_tools.py
custom_inherit/_doc_parse_tools/rest_parse_tools.py
custom_inherit/_doc_parse_tools/section_items.py
custom_inherit-2.4.1.dist-info/LICENSE.md
custom_inherit-2.4.1.dist-info/METADATA
custom_inherit-2.4.1.dist-info/WHEEL
custom_inherit-2.4.1.dist-info/top_level.txt
custom_inherit-2.4.1.dist-info/RECORD
