Metadata-Version: 2.1
Name: custom-inherit
Version: 2.4.1
Summary: A Python package that provides customized docstring inheritance       schemes between derived classes and their parents.
Home-page: https://github.com/rsokl/custom_inherit
Download-URL: https://github.com/rsokl/custom_inherit/tarball/2.4.1
Author: @rsokl
Author-email: rsoklaski@gmail.com
License: MIT
Classifier: Development Status :: 4 - Beta
Classifier: License :: OSI Approved :: MIT License
Classifier: Operating System :: OS Independent
Classifier: Programming Language :: Python :: 2.7
Classifier: Programming Language :: Python :: 3.7
Classifier: Programming Language :: Python :: 3.8
Classifier: Programming Language :: Python :: 3.9
Classifier: Programming Language :: Python :: 3.10
Classifier: Programming Language :: Python :: 3.11
License-File: LICENSE.md
